cellular_automata_grids/__init__.py
cellular_automata_grids/__main__.py
cellular_automata_grids/settings.py
cellular_automata_grids/grids/__init__.py
cellular_automata_grids/grids/base_grid.py
cellular_automata_grids/grids/hexagonal_grid.py
cellular_automata_grids/grids/square_grid.py
cellular_automata_grids/grids/square_grid_alt.py
cellular_automata_grids/grids/teminal_square_grid.py
cellular_automata_grids/grids/triangular_grid.py
cellular_automata_grids/homemade/__init__.py
cellular_automata_grids/homemade/triangular_grid_generator.py
cellular_automata_grids/vendor/hexagons.py
cellular_automata_grids-0.1.5.dist-info/LICENSE
cellular_automata_grids-0.1.5.dist-info/METADATA
cellular_automata_grids-0.1.5.dist-info/WHEEL
cellular_automata_grids-0.1.5.dist-info/entry_points.txt
cellular_automata_grids-0.1.5.dist-info/top_level.txt
cellular_automata_grids-0.1.5.dist-info/RECORD
