Metadata-Version: 2.2
Name: cellular-automata-grids
Version: 0.1.5
Summary: Miscellaneous grids for cellular automata..
Author-email: Jacek Siciarek <siciarek@gmail.com>
Maintainer-email: Jacek Siciarek <siciarek@gmail.com>
License:                     GNU GENERAL PUBLIC LICENSE
Project-URL: Homepage, https://github.com/siciarek/cellular-automata-grids/
Project-URL: Documentation, https://github.com/siciarek/cellular-automata-grids/tree/master/docs
Project-URL: Repository, https://github.com/siciarek/cellular-automata-grids
Project-URL: Changelog, https://github.com/siciarek/cellular-automata-grids/blob/master/docs/change-log.md
Classifier: Development Status :: 4 - Beta
Classifier: Programming Language :: Python :: 3.9
Classifier: Programming Language :: Python :: 3.10
Classifier: Programming Language :: Python :: 3.11
Classifier: Programming Language :: Python :: 3.12
Requires-Python: <3.13,>=3.9
License-File: LICENSE
Requires-Dist: click~=8.1.8
Requires-Dist: pygame~=2.6.1
Requires-Dist: pyopengl
Requires-Dist: pyopengl-accelerate
Provides-Extra: doc
Requires-Dist: mkdocs~=1.5.3; extra == "doc"
Requires-Dist: mkdocs-material~=9.5.17; extra == "doc"
Requires-Dist: mkdocs-material-extensions~=1.3.1; extra == "doc"
Requires-Dist: pip-tools~=7.4.1; extra == "doc"
Provides-Extra: test
Requires-Dist: pytest~=8.0.2; extra == "test"
Requires-Dist: pytest-xdist~=3.5.0; extra == "test"
Requires-Dist: pytest-cov~=4.1.0; extra == "test"
Requires-Dist: pytest-mock~=3.12.0; extra == "test"
Requires-Dist: tox~=4.14.2; extra == "test"
Provides-Extra: analysis
Requires-Dist: radon~=6.0.1; extra == "analysis"
Requires-Dist: ruff~=0.3.4; extra == "analysis"
Requires-Dist: pre_commit~=3.6.2; extra == "analysis"
Requires-Dist: bandit[toml]~=1.7.8; extra == "analysis"
Requires-Dist: licensecheck~=2024.2; extra == "analysis"
Provides-Extra: dev
Requires-Dist: cellular-automata-grids[test]; extra == "dev"
Requires-Dist: cellular-automata-grids[analysis]; extra == "dev"
Requires-Dist: cellular-automata-grids[doc]; extra == "dev"
